onn4arg/__init__.py
onn4arg/aln2txt.pl
onn4arg/download-model.sh
onn4arg/fa2lst.pl
onn4arg/model.py
onn4arg/predict.py
onn4arg/predict.sh
onn4arg/run.sh
onn4arg-1.0.dist-info/LICENSE
onn4arg-1.0.dist-info/METADATA
onn4arg-1.0.dist-info/WHEEL
onn4arg-1.0.dist-info/top_level.txt
onn4arg-1.0.dist-info/RECORD
